juham_core/__init__.py
juham_core/juham.py
juham_core/juham_cloud.py
juham_core/juham_thread.py
juham_core/juham_ts.py
juham_core/py.typed
juham_core/timeutils.py
juham_core-0.2.7.dist-info/licenses/LICENSE.rst
juham_core-0.2.7.dist-info/METADATA
juham_core-0.2.7.dist-info/WHEEL
juham_core-0.2.7.dist-info/top_level.txt
juham_core-0.2.7.dist-info/RECORD
