Metadata-Version: 2.4
Name: juham-core
Version: 0.2.7
Summary: Juha's Ultimate Home Automation Core
Author-email: J Meskanen <juham.api@gmail.com>
Maintainer-email: "J. Meskanen" <juham.api@gmail.com>
License-Expression: MIT
Project-URL: Homepage, https://gitlab.com/juham/juham/juham_core
Project-URL: Bug Reports, https://gitlab.com/juham/juham/juham_core
Project-URL: Funding, https://meskanen.com
Project-URL: Say Thanks!, http://meskanen.com
Project-URL: Source, https://gitlab.com/juham/juham/juham_core
Keywords: home,automation,juham
Classifier: Development Status :: 4 - Beta
Classifier: Intended Audience :: Developers
Classifier: Topic :: Software Development
Classifier: Programming Language :: Python :: 3.8
Requires-Python: >=3.8
License-File: LICENSE.rst
Requires-Dist: masterpiece>=0.1.52
Requires-Dist: masterpiece_influx>=0.1.13
Requires-Dist: masterpiece_pahomqtt>=0.1.11
Requires-Dist: requests>=2.31
Requires-Dist: pytz>=2024.1
Requires-Dist: importlib-metadata
Provides-Extra: dev
Requires-Dist: check-manifest; extra == "dev"
Requires-Dist: coverage>=7.0; extra == "dev"
Dynamic: license-file
